README.md
setup.py
pyrenko/__init__.py
pyrenko/pyrenko.py
pyrenko.egg-info/PKG-INFO
pyrenko.egg-info/SOURCES.txt
pyrenko.egg-info/dependency_links.txt
pyrenko.egg-info/not-zip-safe
pyrenko.egg-info/requires.txt
pyrenko.egg-info/top_level.txt