Metadata-Version: 2.1
Name: pyrenko
Version: 0.1
Summary: Renko calculation and chart
Home-page: UNKNOWN
Author: Dennis Lee
Author-email: dennislwm@gmail.com
License: MIT
Platform: UNKNOWN
